rest_wind/__init__.py
rest_wind/apps.py
rest_wind/locale/ar/LC_MESSAGES/django.po
rest_wind/locale/cn/LC_MESSAGES/django.po
rest_wind/locale/de/LC_MESSAGES/django.po
rest_wind/locale/es/LC_MESSAGES/django.po
rest_wind/locale/fr/LC_MESSAGES/django.po
rest_wind/locale/ru/LC_MESSAGES/django.po
rest_wind/locale/tr/LC_MESSAGES/django.po
rest_wind/static/rest_wind/.prettierrc
rest_wind/static/rest_wind/README.md
rest_wind/static/rest_wind/css/app.css
rest_wind/static/rest_wind/css/pygments.css
rest_wind/static/rest_wind/css/styles.css
rest_wind/static/rest_wind/package-lock.json
rest_wind/static/rest_wind/package.json
rest_wind/templates/django_filters/rest_framework/form.html
rest_wind/templates/rest_framework/base.html
rest_wind/templates/rest_framework/components/dialogs.html
rest_wind/templates/rest_framework/components/field_errors.html
rest_wind/templates/rest_framework/components/form.html
rest_wind/templates/rest_framework/components/languages.html
rest_wind/templates/rest_framework/components/messages.html
rest_wind/templates/rest_framework/components/themes.html
rest_wind/templates/rest_framework/filters/base.html
rest_wind/templates/rest_framework/filters/ordering.html
rest_wind/templates/rest_framework/filters/search.html
rest_wind/templates/rest_framework/horizontal/checkbox.html
rest_wind/templates/rest_framework/horizontal/checkbox_multiple.html
rest_wind/templates/rest_framework/horizontal/fieldset.html
rest_wind/templates/rest_framework/horizontal/input.html
rest_wind/templates/rest_framework/horizontal/radio.html
rest_wind/templates/rest_framework/horizontal/select.html
rest_wind/templates/rest_framework/horizontal/select_multiple.html
rest_wind/templates/rest_framework/horizontal/textarea.html
rest_wind/templates/rest_framework/inline/checkbox.html
rest_wind/templates/rest_framework/inline/checkbox_multiple.html
rest_wind/templates/rest_framework/inline/fieldset.html
rest_wind/templates/rest_framework/inline/input.html
drf_restwind-1.3.0.dist-info/METADATA
drf_restwind-1.3.0.dist-info/WHEEL
drf_restwind-1.3.0.dist-info/licenses/LICENSE
drf_restwind-1.3.0.dist-info/RECORD
