Metadata-Version: 2.4
Name: drf-restwind
Version: 1.3.0
Summary: drf-restwind, a modern re-imagining of the Django REST Framework utilizes TailwindCSS and DaisyUI to provide flexible and customizable UI solutions with minimal coding effort.
License: MIT
License-File: LICENSE
Author: Yousef Abu Shanab
Author-email: josephyousef249@gmail.com
Requires-Python: >=3.11
Classifier: Development Status :: 5 - Production/Stable
Classifier: Environment :: Web Environment
Classifier: Framework :: Django
Classifier: Framework :: Django :: 5.2
Classifier: Framework :: Django :: 6.0
Classifier: Intended Audience :: Developers
Classifier: License :: OSI Approved :: MIT License
Classifier: Operating System :: OS Independent
Classifier: Programming Language :: Python
Classifier: Programming Language :: Python :: 3
Classifier: Programming Language :: Python :: 3.11
Classifier: Programming Language :: Python :: 3.12
Classifier: Programming Language :: Python :: 3.13
Classifier: Programming Language :: Python :: 3.14
Classifier: Programming Language :: Python :: 3 :: Only
Classifier: Topic :: Internet :: WWW/HTTP
Requires-Dist: django (>=5.2.5)
Requires-Dist: djangorestframework (>=3.16.1)
Project-URL: Documentation, https://github.com/youzarsiph/drf-restwind
Project-URL: Homepage, https://github.com/youzarsiph/drf-restwind
Project-URL: Repository, https://github.com/youzarsiph/drf-restwind
